Lab1/vending_machine/vending_machine_def.v
// Title         : vending_machine_def.v
// Author      : Jae-Eon Jo (Jojaeeon@postech.ac.kr) 
//					Dongup Kwon (nankdu7@postech.ac.kr)

// Macro constants (prefix k & CamelCase)
`define kTotalBits 32
  
`define kItemBits 8
`define kNumItems 4

`define kCoinBits 8
`define kNumCoins 3

`define kWaitTime 10

Lab1/vending_machine/change_state.v
`include "vending_machine_def.v"


module change_state(clk,reset_n,current_total_nxt,input_total, output_total, return_total, current_total);

	input clk;
	input reset_n;
	input [`kTotalBits-1:0] current_total_nxt;
	input reg  [`kTotalBits-1:0] input_total, output_total, return_total;
	output reg [`kTotalBits-1:0] current_total;
	
	// Sequential circuit to reset or update the states
	always @(posedge clk) begin
		if (!reset_n) begin
			// TODO: reset all states.
            current_total <= 0;
		end
		else begin
			// TODO: update all states.
            current_total <= current_total_nxt + input_total - return_total - output_total;
		end
	end
endmodule

Lab1/vending_machine/calculate_current_state.v
`include "vending_machine_def.v"
	

module calculate_current_state(i_input_coin,i_select_item,item_price,coin_value,current_total,
current_total_nxt,input_total, output_total, return_total,o_return_coin,o_available_item,o_output_item);


	
	input [`kNumCoins-1:0] i_input_coin, o_return_coin;
	input [`kNumItems-1:0]	i_select_item;			
	input [31:0] item_price [`kNumItems-1:0];
	input [31:0] coin_value [`kNumCoins-1:0];	
	input [`kTotalBits-1:0] current_total;
	output reg [`kTotalBits-1:0] input_total, output_total, return_total;
	output reg [`kNumItems-1:0] o_available_item, o_output_item;
    output reg [`kTotalBits-1:0] current_total_nxt;
	integer i;

    initial begin
        input_total = 0;
        output_total = 0;
        return_total = 0;
    end
	
	// Combinational logic for the next states
	always @(*) begin
		// TODO: current_total_nxt
		// You don't have to worry about concurrent activations in each input vector (or array).
		// Calculate the next current_total state.

        input_total = 0;
        output_total = 0;
        return_total = 0;

        // 1. coin input
        // 2. coin return
        for (i = 0; i < `kNumCoins; i = i + 1) begin
            if (i_input_coin[i]) begin
                input_total = input_total + coin_value[i];
            end
            if (o_return_coin[i]) begin
                return_total = return_total + coin_value[i];
            end
        end
        // 3. item selection
        for (i = 0; i < `kNumItems; i = i + 1) begin
            if (i_select_item[i] && item_price[i] <= current_total) begin
                output_total = output_total + item_price[i];
            end
        end
        current_total_nxt = current_total;
	end

	
	
	// Combinational logic for the outputs
	always @(*) begin
        // TODO: o_available_item
        // TODO: o_output_item
		o_available_item = 0; // initiate
        o_output_item = 0; // initiate
        for (i = 0; i < `kNumItems; i = i + 1) begin
            if (item_price[i] <= current_total) begin
                o_available_item[i] = 1;
            end
            if (i_select_item[i] && item_price[i] <= current_total) begin
                o_output_item[i] = 1;
            end
        end
	end
 
	


endmodule

Lab1/vending_machine/check_time_and_coin.v
`include "vending_machine_def.v"

	

module check_time_and_coin(i_input_coin,i_select_item,clk,reset_n,o_return_coin, current_total, i_trigger_return, item_price, coin_value);
	input clk;
	input reset_n;
	input [`kNumCoins-1:0] i_input_coin;
	input [`kNumItems-1:0]	i_select_item;
    input [`kTotalBits-1:0] current_total; //
    input i_trigger_return; //
	input [31:0] item_price [`kNumItems-1:0]; //
	input [31:0] coin_value [`kNumCoins-1:0]; //
	output reg [`kNumCoins-1:0] o_return_coin;
	reg signed [31:0] wait_time;
    integer i;
	integer temp_return_total;
    integer waitForThreeCycles = 0;

	// initiate values
	initial begin
		// TODO: initiate values
        wait_time = `kWaitTime;
	end

    // TODO: o_return_coin
    always @(*) begin
		temp_return_total = 0;
        o_return_coin = 0;
        if (waitForThreeCycles == 3 || wait_time < 0) begin // calculate return coin by coin when time = 0 or return triggered
            // if (current_total / coin_value[2] > 0) begin
            //     o_return_coin[2] = 1;
            // end
            // else if ((current_total % coin_value[2]) / coin_value[1] > 0) begin
            //     o_return_coin[1] = 1;
            // end
            // else if ((current_total % coin_value[1]) / coin_value[0] > 0) begin
            //     o_return_coin[0] = 1;
            // end
            for (i = `kNumCoins - 1; i >= 0; i = i - 1) begin
				if(coin_value[i] <= current_total - temp_return_total) begin
					o_return_coin[i] = 1;
					temp_return_total = temp_return_total + coin_value[i];
				end
			end
        end
    end

	always @(posedge clk) begin
        if (i_trigger_return) begin
            waitForThreeCycles <= waitForThreeCycles + 1;
        end
        else begin
            waitForThreeCycles <= 0;
        end
            
		if (!reset_n) begin
            // TODO: reset all states.
            wait_time <= `kWaitTime;
		end
		else begin
            wait_time <= wait_time - 1;
		end
        
        // TODO: update coin return time
        if (i_input_coin != 0) begin
            wait_time <= `kWaitTime;
        end
        for (i = 0; i < `kNumCoins; i = i + 1) begin
            if (i_input_coin[i]) begin
                wait_time <= `kWaitTime;
            end
        end
        for (i = 0; i < `kNumItems; i = i + 1) begin
            if (i_select_item[i] && item_price[i] <= current_total) begin
                wait_time <= `kWaitTime;
            end
        end
	end
endmodule

Lab1/vending_machine/vending_machine.v
// Title         : vending_machine.v
// Author      : Jae-Eon Jo (Jojaeeon@postech.ac.kr) 
//			     Dongup Kwon (nankdu7@postech.ac.kr) (2015.03.30)
//			     Jaehun Ryu (jaehunryu@postech.ac.kr) (2021.03.07)

`include "vending_machine_def.v"


module vending_machine (
	clk,							// Clock signal
	reset_n,						// Reset signal (active-low)

	i_input_coin,				// coin is inserted.
	i_select_item,				// item is selected.
	i_trigger_return,			// change-return is triggered 

	o_available_item,			// Sign of the item availability
	o_output_item,			// Sign of the item withdrawal
	o_return_coin				// Sign of the coin return
);

	// Ports Declaration
	// Do not modify the module interface
	input clk;
	input reset_n;
	
	input [`kNumCoins-1:0] i_input_coin;
	input [`kNumItems-1:0] i_select_item;
	input i_trigger_return;
		
	output [`kNumItems-1:0] o_available_item;
	output [`kNumItems-1:0] o_output_item;
	output [`kNumCoins-1:0] o_return_coin;


	

	// Do not modify the values.
	wire [31:0] item_price [`kNumItems-1:0];	// Price of each item
	wire [31:0] coin_value [`kNumCoins-1:0];	// Value of each coin
	assign item_price[0] = 400;
	assign item_price[1] = 500;
	assign item_price[2] = 1000;
	assign item_price[3] = 2000;
	assign coin_value[0] = 100;
	assign coin_value[1] = 500;
	assign coin_value[2] = 1000;

	// Internal states. You may add your own net variables.
	wire [`kTotalBits-1:0] current_total;
	
	// Next internal states. You may add your own net variables.
	wire [`kTotalBits-1:0] current_total_nxt;

	
	// Variables. You may add more your own net variables.s
	wire [`kTotalBits-1:0] input_total, output_total, return_total;

	// This module interface, structure, and given a number of modules are not mandatory but recommended.
	// However, Implementations that use modules are mandatory.
		
  	check_time_and_coin check_time_and_coin_module(.i_input_coin(i_input_coin),
  									.i_select_item(i_select_item),
									.clk(clk),
									.reset_n(reset_n),
									.o_return_coin(o_return_coin),
                                    .current_total(current_total), 
                                    .i_trigger_return(i_trigger_return), 
                                    .item_price(item_price),
                                    .coin_value(coin_value));

	calculate_current_state calculate_current_state_module(.i_input_coin(i_input_coin),
										.i_select_item(i_select_item),
										.item_price(item_price),
										.coin_value(coin_value),
										.current_total(current_total),
										.current_total_nxt(current_total_nxt),
                                        .input_total(input_total),
                                        .output_total(output_total),
                                        .return_total(return_total),
                                        .o_return_coin(o_return_coin),
										.o_available_item(o_available_item),
										.o_output_item(o_output_item));
	
  	change_state change_state_module(
						.clk(clk),
						.reset_n(reset_n),
						.current_total_nxt(current_total_nxt),
                        .input_total(input_total),
                        .output_total(output_total),
                        .return_total(return_total),
						.current_total(current_total));


endmodule

Lab1/vending_machine/waveform.vcd
$version Generated by VerilatedVcd $end
$timescale 1ps $end
 $scope module TOP $end
  $var wire 1 1 clk $end
  $var wire 1 2 reset_n $end
  $var wire 3 3 i_input_coin [2:0] $end
  $var wire 4 4 i_select_item [3:0] $end
  $var wire 1 5 i_trigger_return $end
  $var wire 4 6 o_available_item [3:0] $end
  $var wire 4 7 o_output_item [3:0] $end
  $var wire 3 8 o_return_coin [2:0] $end
  $scope module vending_machine $end
   $var wire 1 1 clk $end
   $var wire 1 2 reset_n $end
   $var wire 3 3 i_input_coin [2:0] $end
   $var wire 4 4 i_select_item [3:0] $end
   $var wire 1 5 i_trigger_return $end
   $var wire 4 6 o_available_item [3:0] $end
   $var wire 4 7 o_output_item [3:0] $end
   $var wire 3 8 o_return_coin [2:0] $end
   $var wire 32 # item_price[0] [31:0] $end
   $var wire 32 $ item_price[1] [31:0] $end
   $var wire 32 % item_price[2] [31:0] $end
   $var wire 32 & item_price[3] [31:0] $end
   $var wire 32 ' coin_value[0] [31:0] $end
   $var wire 32 ( coin_value[1] [31:0] $end
   $var wire 32 ) coin_value[2] [31:0] $end
   $var wire 32 + current_total [31:0] $end
   $var wire 32 + current_total_nxt [31:0] $end
   $var wire 32 9 input_total [31:0] $end
   $var wire 32 : output_total [31:0] $end
   $var wire 32 , return_total [31:0] $end
   $scope module calculate_current_state_module $end
    $var wire 3 3 i_input_coin [2:0] $end
    $var wire 3 8 o_return_coin [2:0] $end
    $var wire 4 4 i_select_item [3:0] $end
    $var wire 32 # item_price[0] [31:0] $end
    $var wire 32 $ item_price[1] [31:0] $end
    $var wire 32 % item_price[2] [31:0] $end
    $var wire 32 & item_price[3] [31:0] $end
    $var wire 32 ' coin_value[0] [31:0] $end
    $var wire 32 ( coin_value[1] [31:0] $end
    $var wire 32 ) coin_value[2] [31:0] $end
    $var wire 32 + current_total [31:0] $end
    $var wire 32 9 input_total [31:0] $end
    $var wire 32 : output_total [31:0] $end
    $var wire 32 , return_total [31:0] $end
    $var wire 4 6 o_available_item [3:0] $end
    $var wire 4 7 o_output_item [3:0] $end
    $var wire 32 + current_total_nxt [31:0] $end
    $var wire 32 * i [31:0] $end
   $upscope $end
   $scope module change_state_module $end
    $var wire 1 1 clk $end
    $var wire 1 2 reset_n $end
    $var wire 32 + current_total_nxt [31:0] $end
    $var wire 32 9 input_total [31:0] $end
    $var wire 32 : output_total [31:0] $end
    $var wire 32 , return_total [31:0] $end
    $var wire 32 + current_total [31:0] $end
   $upscope $end
   $scope module check_time_and_coin_module $end
    $var wire 1 1 clk $end
    $var wire 1 2 reset_n $end
    $var wire 3 3 i_input_coin [2:0] $end
    $var wire 4 4 i_select_item [3:0] $end
    $var wire 32 + current_total [31:0] $end
    $var wire 1 5 i_trigger_return $end
    $var wire 32 # item_price[0] [31:0] $end
    $var wire 32 $ item_price[1] [31:0] $end
    $var wire 32 % item_price[2] [31:0] $end
    $var wire 32 & item_price[3] [31:0] $end
    $var wire 32 ' coin_value[0] [31:0] $end
    $var wire 32 ( coin_value[1] [31:0] $end
    $var wire 32 ) coin_value[2] [31:0] $end
    $var wire 3 8 o_return_coin [2:0] $end
    $var wire 32 - wait_time [31:0] $end
    $var wire 32 . i [31:0] $end
    $var wire 32 / temp_return_total [31:0] $end
    $var wire 32 0 waitForThreeCycles [31:0] $end
   $upscope $end
  $upscope $end
 $upscope $end
$enddefinitions $end


#0
b00000000000000000000000110010000 #
b00000000000000000000000111110100 $
b00000000000000000000001111101000 %
b00000000000000000000011111010000 &
b00000000000000000000000001100100 '
b00000000000000000000000111110100 (
b00000000000000000000001111101000 )
b00000000000000000000000000000100 *
b11000110010101111110111011101001 +
b00000000000000000000000000000000 ,
b00000000000000000000000000001010 -
b11100100100101011010110000101011 .
b00000000000000000000000000000000 /
b00000000000000000000000000000000 0
11
12
b000 3
b0000 4
05
b1111 6
b0000 7
b000 8
b00000000000000000000000000000000 9
b00000000000000000000000000000000 :
#1
01
#2
b00000000000000000000000000000000 +
b00000000000000000000000000000100 .
11
02
b0000 6
#3
01
#4
11
#5
01
#6
b00000000000000000000000000001001 -
11
12
#7
01
#8
b00000000000000000000000001100100 +
b00000000000000000000000000001010 -
11
b001 3
b00000000000000000000000001100100 9
#9
01
#10
b00000000000000000000000000001001 -
11
b000 3
b00000000000000000000000000000000 9
#11
01
#12
b00000000000000000000000011001000 +
b00000000000000000000000000001010 -
11
b001 3
b00000000000000000000000001100100 9
#13
01
#14
b00000000000000000000000000001001 -
11
b000 3
b00000000000000000000000000000000 9
#15
01
#16
b00000000000000000000000100101100 +
b00000000000000000000000000001010 -
11
b001 3
b00000000000000000000000001100100 9
#17
01
#18
b00000000000000000000000000001001 -
11
b000 3
b00000000000000000000000000000000 9
#19
01
#20
b00000000000000000000000110010000 +
b00000000000000000000000000001010 -
11
b001 3
b0001 6
b00000000000000000000000001100100 9
#21
01
#22
b00000000000000000000000000001001 -
11
b000 3
b00000000000000000000000000000000 9
#23
01
#24
b00000000000000000000000111110100 +
b00000000000000000000000000001010 -
11
b001 3
b0011 6
b00000000000000000000000001100100 9
#25
01
#26
b00000000000000000000000000001001 -
11
b000 3
b00000000000000000000000000000000 9
#27
01
#28
b00000000000000000000000000001000 -
11
#29
01
#30
b00000000000000000000000000000000 +
b00000000000000000000000000001010 -
11
02
b0000 6
#31
01
#32
11
#33
01
#34
b00000000000000000000000000001001 -
11
12
#35
01
#36
b00000000000000000000000111110100 +
b00000000000000000000000000001010 -
11
b010 3
b0011 6
b00000000000000000000000111110100 9
#37
01
#38
b00000000000000000000000000001001 -
11
b000 3
b00000000000000000000000000000000 9
#39
01
#40
b00000000000000000000001111101000 +
b00000000000000000000000000001010 -
11
b010 3
b0111 6
b00000000000000000000000111110100 9
#41
01
#42
b00000000000000000000000000001001 -
11
b000 3
b00000000000000000000000000000000 9
#43
01
#44
b00000000000000000000010111011100 +
b00000000000000000000000000001010 -
11
b010 3
b00000000000000000000000111110100 9
#45
01
#46
b00000000000000000000000000001001 -
11
b000 3
b00000000000000000000000000000000 9
#47
01
#48
b00000000000000000000011111010000 +
b00000000000000000000000000001010 -
11
b010 3
b1111 6
b00000000000000000000000111110100 9
#49
01
#50
b00000000000000000000000000001001 -
11
b000 3
b00000000000000000000000000000000 9
#51
01
#52
b00000000000000000000000000001000 -
11
#53
01
#54
b00000000000000000000000000000000 +
b00000000000000000000000000001010 -
11
02
b0000 6
#55
01
#56
11
#57
01
#58
b00000000000000000000000000001001 -
11
12
#59
01
#60
b00000000000000000000001111101000 +
b00000000000000000000000000001010 -
11
b100 3
b0111 6
b00000000000000000000001111101000 9
#61
01
#62
b00000000000000000000000000001001 -
11
b000 3
b00000000000000000000000000000000 9
#63
01
#64
b00000000000000000000011111010000 +
b00000000000000000000000000001010 -
11
b100 3
b1111 6
b00000000000000000000001111101000 9
#65
01
#66
b00000000000000000000000000001001 -
11
b000 3
b00000000000000000000000000000000 9
#67
01
#68
b00000000000000000000000000001000 -
11
#69
01
#70
b00000000000000000000000000000000 +
b00000000000000000000000000001010 -
11
02
b0000 6
#71
01
#72
11
#73
01
#74
b00000000000000000000000000001001 -
11
12
#75
01
#76
b00000000000000000000001111101000 +
b00000000000000000000000000001010 -
11
b100 3
b0111 6
b00000000000000000000001111101000 9
#77
01
#78
b00000000000000000000000000001001 -
11
b000 3
b00000000000000000000000000000000 9
#79
01
#80
b00000000000000000000011111010000 +
b00000000000000000000000000001010 -
11
b100 3
b1111 6
b00000000000000000000001111101000 9
#81
01
#82
b00000000000000000000000000001001 -
11
b000 3
b00000000000000000000000000000000 9
#83
01
#84
b00000000000000000000101110111000 +
b00000000000000000000000000001010 -
11
b100 3
b00000000000000000000001111101000 9
#85
01
#86
b00000000000000000000000000001001 -
11
b000 3
b00000000000000000000000000000000 9
#87
01
#88
b00000000000000000000101000101000 +
b00000000000000000000000000001010 -
11
b0001 4
b0001 7
b00000000000000000000000110010000 :
#89
01
#90
b00000000000000000000000000001001 -
11
b0000 4
b0000 7
b00000000000000000000000000000000 :
#91
01
#92
b00000000000000000000000000001000 -
11
#93
01
#94
b00000000000000000000000000000111 -
11
#95
01
#96
b00000000000000000000100010011000 +
b00000000000000000000000000001010 -
11
b0001 4
b0001 7
b00000000000000000000000110010000 :
#97
01
#98
b00000000000000000000000000001001 -
11
b0000 4
b0000 7
b00000000000000000000000000000000 :
#99
01
#100
b00000000000000000000000000001000 -
11
#101
01
#102
b00000000000000000000000000000111 -
11
#103
01
#104
b00000000000000000000011100001000 +
b00000000000000000000000000001010 -
11
b0001 4
b0111 6
b0001 7
b00000000000000000000000110010000 :
#105
01
#106
b00000000000000000000000000001001 -
11
b0000 4
b0000 7
b00000000000000000000000000000000 :
#107
01
#108
b00000000000000000000000000001000 -
11
#109
01
#110
b00000000000000000000000000000111 -
11
#111
01
#112
b00000000000000000000010101111000 +
b00000000000000000000000000001010 -
11
b0001 4
b0001 7
b00000000000000000000000110010000 :
#113
01
#114
b00000000000000000000000000001001 -
11
b0000 4
b0000 7
b00000000000000000000000000000000 :
#115
01
#116
b00000000000000000000000000001000 -
11
#117
01
#118
b00000000000000000000000000000111 -
11
#119
01
#120
b00000000000000000000001111101000 +
b00000000000000000000000000001010 -
11
b0001 4
b0001 7
b00000000000000000000000110010000 :
#121
01
#122
b00000000000000000000000000001001 -
11
b0000 4
b0000 7
b00000000000000000000000000000000 :
#123
01
#124
b00000000000000000000000000001000 -
11
#125
01
#126
b00000000000000000000000000000111 -
11
#127
01
#128
b00000000000000000000001001011000 +
b00000000000000000000000000001010 -
11
b0001 4
b0011 6
b0001 7
b00000000000000000000000110010000 :
#129
01
#130
b00000000000000000000000000001001 -
11
b0000 4
b0000 7
b00000000000000000000000000000000 :
#131
01
#132
b00000000000000000000000000001000 -
11
#133
01
#134
b00000000000000000000000000000111 -
11
#135
01
#136
b00000000000000000000000011001000 +
b00000000000000000000000000001010 -
11
b0001 4
b0000 6
#137
01
#138
b00000000000000000000000000001001 -
11
b0000 4
#139
01
#140
b00000000000000000000000000001000 -
11
#141
01
#142
b00000000000000000000000000000111 -
11
#143
01
#144
b00000000000000000000000000000110 -
11
#145
01
#146
b00000000000000000000000000000101 -
11
#147
01
#148
b00000000000000000000010010110000 +
b00000000000000000000000000001010 -
11
b100 3
b0111 6
b00000000000000000000001111101000 9
#149
01
#150
b00000000000000000000000000001001 -
11
b000 3
b00000000000000000000000000000000 9
#151
01
#152
b00000000000000000000100010011000 +
b00000000000000000000000000001010 -
11
b100 3
b1111 6
b00000000000000000000001111101000 9
#153
01
#154
b00000000000000000000000000001001 -
11
b000 3
b00000000000000000000000000000000 9
#155
01
#156
b00000000000000000000110010000000 +
b00000000000000000000000000001010 -
11
b100 3
b00000000000000000000001111101000 9
#157
01
#158
b00000000000000000000000000001001 -
11
b000 3
b00000000000000000000000000000000 9
#159
01
#160
b00000000000000000000101010001100 +
b00000000000000000000000000001010 -
11
b0010 4
b0010 7
b00000000000000000000000111110100 :
#161
01
#162
b00000000000000000000000000001001 -
11
b0000 4
b0000 7
b00000000000000000000000000000000 :
#163
01
#164
b00000000000000000000000000001000 -
11
#165
01
#166
b00000000000000000000000000000111 -
11
#167
01
#168
b00000000000000000000100010011000 +
b00000000000000000000000000001010 -
11
b0010 4
b0010 7
b00000000000000000000000111110100 :
#169
01
#170
b00000000000000000000000000001001 -
11
b0000 4
b0000 7
b00000000000000000000000000000000 :
#171
01
#172
b00000000000000000000000000001000 -
11
#173
01
#174
b00000000000000000000000000000111 -
11
#175
01
#176
b00000000000000000000011010100100 +
b00000000000000000000000000001010 -
11
b0010 4
b0111 6
b0010 7
b00000000000000000000000111110100 :
#177
01
#178
b00000000000000000000000000001001 -
11
b0000 4
b0000 7
b00000000000000000000000000000000 :
#179
01
#180
b00000000000000000000000000001000 -
11
#181
01
#182
b00000000000000000000000000000111 -
11
#183
01
#184
b00000000000000000000010010110000 +
b00000000000000000000000000001010 -
11
b0010 4
b0010 7
b00000000000000000000000111110100 :
#185
01
#186
b00000000000000000000000000001001 -
11
b0000 4
b0000 7
b00000000000000000000000000000000 :
#187
01
#188
b00000000000000000000000000001000 -
11
#189
01
#190
b00000000000000000000000000000111 -
11
#191
01
#192
b00000000000000000000001010111100 +
b00000000000000000000000000001010 -
11
b0010 4
b0011 6
b0010 7
b00000000000000000000000111110100 :
#193
01
#194
b00000000000000000000000000001001 -
11
b0000 4
b0000 7
b00000000000000000000000000000000 :
#195
01
#196
b00000000000000000000000000001000 -
11
#197
01
#198
b00000000000000000000000000000111 -
11
#199
01
#200
b00000000000000000000000011001000 +
b00000000000000000000000000001010 -
11
b0010 4
b0000 6
#201
01
#202
b00000000000000000000000000001001 -
11
b0000 4
#203
01
#204
b00000000000000000000000000001000 -
11
#205
01
#206
b00000000000000000000000000000111 -
11
#207
01
#208
b00000000000000000000000100101100 +
b00000000000000000000000000001010 -
11
b001 3
b00000000000000000000000001100100 9
#209
01
#210
b00000000000000000000000000001001 -
11
b000 3
b00000000000000000000000000000000 9
#211
01
#212
b00000000000000000000000110010000 +
b00000000000000000000000000001010 -
11
b001 3
b0001 6
b00000000000000000000000001100100 9
#213
01
#214
b00000000000000000000000000001001 -
11
b000 3
b00000000000000000000000000000000 9
#215
01
#216
b00000000000000000000010101111000 +
b00000000000000000000000000001010 -
11
b100 3
b0111 6
b00000000000000000000001111101000 9
#217
01
#218
b00000000000000000000000000001001 -
11
b000 3
b00000000000000000000000000000000 9
#219
01
#220
b00000000000000000000100101100000 +
b00000000000000000000000000001010 -
11
b100 3
b1111 6
b00000000000000000000001111101000 9
#221
01
#222
b00000000000000000000000000001001 -
11
b000 3
b00000000000000000000000000000000 9
#223
01
#224
b00000000000000000000110101001000 +
b00000000000000000000000000001010 -
11
b100 3
b00000000000000000000001111101000 9
#225
01
#226
b00000000000000000000000000001001 -
11
b000 3
b00000000000000000000000000000000 9
#227
01
#228
b00000000000000000000100101100000 +
b00000000000000000000000000001010 -
11
b0100 4
b0100 7
b00000000000000000000001111101000 :
#229
01
#230
b00000000000000000000000000001001 -
11
b0000 4
b0000 7
b00000000000000000000000000000000 :
#231
01
#232
b00000000000000000000000000001000 -
11
#233
01
#234
b00000000000000000000000000000111 -
11
#235
01
#236
b00000000000000000000010101111000 +
b00000000000000000000000000001010 -
11
b0100 4
b0111 6
b0100 7
b00000000000000000000001111101000 :
#237
01
#238
b00000000000000000000000000001001 -
11
b0000 4
b0000 7
b00000000000000000000000000000000 :
#239
01
#240
b00000000000000000000000000001000 -
11
#241
01
#242
b00000000000000000000000000000111 -
11
#243
01
#244
b00000000000000000000000110010000 +
b00000000000000000000000000001010 -
11
b0100 4
b0001 6
#245
01
#246
b00000000000000000000000000001001 -
11
b0000 4
#247
01
#248
b00000000000000000000000000001000 -
11
#249
01
#250
b00000000000000000000000000000111 -
11
#251
01
#252
b00000000000000000000010101111000 +
b00000000000000000000000000001010 -
11
b100 3
b0111 6
b00000000000000000000001111101000 9
#253
01
#254
b00000000000000000000000000001001 -
11
b000 3
b00000000000000000000000000000000 9
#255
01
#256
b00000000000000000000100101100000 +
b00000000000000000000000000001010 -
11
b100 3
b1111 6
b00000000000000000000001111101000 9
#257
01
#258
b00000000000000000000000000001001 -
11
b000 3
b00000000000000000000000000000000 9
#259
01
#260
b00000000000000000000110101001000 +
b00000000000000000000000000001010 -
11
b100 3
b00000000000000000000001111101000 9
#261
01
#262
b00000000000000000000000000001001 -
11
b000 3
b00000000000000000000000000000000 9
#263
01
#264
b00000000000000000000010101111000 +
b00000000000000000000000000001010 -
11
b1000 4
b0111 6
#265
01
#266
b00000000000000000000000000001001 -
11
b0000 4
#267
01
#268
b00000000000000000000000000001000 -
11
#269
01
#270
b00000000000000000000000000000111 -
11
#271
01
#272
b00000000000000000000100101100000 +
b00000000000000000000000000001010 -
11
b100 3
b1111 6
b00000000000000000000001111101000 9
#273
01
#274
b00000000000000000000000000001001 -
11
b000 3
b00000000000000000000000000000000 9
#275
01
#276
b00000000000000000000000110010000 +
b00000000000000000000000000001010 -
11
b1000 4
b0001 6
#277
01
#278
b00000000000000000000000000001001 -
11
b0000 4
#279
01
#280
b00000000000000000000000000001000 -
11
#281
01
#282
b00000000000000000000000000000111 -
11
#283
01
#284
b00000000000000000000000111110100 +
b00000000000000000000000000001010 -
11
b001 3
b0011 6
b00000000000000000000000001100100 9
#285
01
#286
b00000000000000000000000000001001 -
11
b000 3
b00000000000000000000000000000000 9
#287
01
#288
b00000000000000000000001001011000 +
b00000000000000000000000000001010 -
11
b001 3
b00000000000000000000000001100100 9
#289
01
#290
b00000000000000000000000000001001 -
11
b000 3
b00000000000000000000000000000000 9
#291
01
#292
b00000000000000000000001010111100 +
b00000000000000000000000000001010 -
11
b001 3
b00000000000000000000000001100100 9
#293
01
#294
b00000000000000000000000000001001 -
11
b000 3
b00000000000000000000000000000000 9
#295
01
#296
b00000000000000000000001100100000 +
b00000000000000000000000000001010 -
11
b001 3
b00000000000000000000000001100100 9
#297
01
#298
b00000000000000000000000000001001 -
11
b000 3
b00000000000000000000000000000000 9
#299
01
#300
b00000000000000000000010100010100 +
b00000000000000000000000000001010 -
11
b010 3
b0111 6
b00000000000000000000000111110100 9
#301
01
#302
b00000000000000000000000000001001 -
11
b000 3
b00000000000000000000000000000000 9
#303
01
#304
b00000000000000000000011100001000 +
b00000000000000000000000000001010 -
11
b010 3
b00000000000000000000000111110100 9
#305
01
#306
b00000000000000000000000000001001 -
11
b000 3
b00000000000000000000000000000000 9
#307
01
#308
b00000000000000000000101011110000 +
b00000000000000000000000000001010 -
11
b100 3
b1111 6
b00000000000000000000001111101000 9
#309
01
#310
b00000000000000000000000000001001 -
11
b000 3
b00000000000000000000000000000000 9
#311
01
#312
b00000000000000000000000000001000 -
11
#313
01
#314
b00000000000000000000000000000111 -
11
#315
01
#316
b00000000000000000000000000000110 -
11
#317
01
#318
b00000000000000000000000000000101 -
11
#319
01
#320
b00000000000000000000000000000100 -
11
#321
01
#322
b00000000000000000000000000000011 -
11
#323
01
#324
b00000000000000000000000000000010 -
11
#325
01
#326
b00000000000000000000000000000001 -
11
#327
01
#328
b00000000000000000000000000000000 -
11
#329
01
#330
b00000000000000000000011001000000 ,
b11111111111111111111111111111111 -
b11111111111111111111111111111111 .
b00000000000000000000011001000000 /
11
b111 8
#331
01
#332
b00000000000000000000010010110000 +
b00000000000000000000010001001100 ,
b11111111111111111111111111111110 -
b00000000000000000000010001001100 /
11
b0111 6
b101 8
#333
01
#334
b00000000000000000000000001100100 +
b00000000000000000000000001100100 ,
b11111111111111111111111111111101 -
b00000000000000000000000001100100 /
11
b0000 6
b001 8
#335
01
#336
b00000000000000000000000000000000 +
b00000000000000000000000000000000 ,
b11111111111111111111111111111100 -
b00000000000000000000000000000000 /
11
b000 8
#337
01
#338
b00000000000000000000000001100100 +
b00000000000000000000000000001010 -
b00000000000000000000000000000100 .
11
b001 3
b00000000000000000000000001100100 9
#339
01
#340
b00000000000000000000000000001001 -
11
b000 3
b00000000000000000000000000000000 9
#341
01
#342
b00000000000000000000000011001000 +
b00000000000000000000000000001010 -
11
b001 3
b00000000000000000000000001100100 9
#343
01
#344
b00000000000000000000000000001001 -
11
b000 3
b00000000000000000000000000000000 9
#345
01
#346
b00000000000000000000000100101100 +
b00000000000000000000000000001010 -
11
b001 3
b00000000000000000000000001100100 9
#347
01
#348
b00000000000000000000000000001001 -
11
b000 3
b00000000000000000000000000000000 9
#349
01
#350
b00000000000000000000001100100000 +
b00000000000000000000000000001010 -
11
b010 3
b0011 6
b00000000000000000000000111110100 9
#351
01
#352
b00000000000000000000000000001001 -
11
b000 3
b00000000000000000000000000000000 9
#353
01
#354
b00000000000000000000010100010100 +
b00000000000000000000000000001010 -
11
b010 3
b0111 6
b00000000000000000000000111110100 9
#355
01
#356
b00000000000000000000000000001001 -
11
b000 3
b00000000000000000000000000000000 9
#357
01
#358
b00000000000000000000011100001000 +
b00000000000000000000000000001010 -
11
b010 3
b00000000000000000000000111110100 9
#359
01
#360
b00000000000000000000000000001001 -
11
b000 3
b00000000000000000000000000000000 9
#361
01
#362
b00000000000000000000101011110000 +
b00000000000000000000000000001010 -
11
b100 3
b1111 6
b00000000000000000000001111101000 9
#363
01
#364
b00000000000000000000000000001001 -
11
b000 3
b00000000000000000000000000000000 9
#365
01
#366
b00000000000000000000111011011000 +
b00000000000000000000000000001010 -
11
b100 3
b00000000000000000000001111101000 9
#367
01
#368
b00000000000000000000000000001001 -
11
b000 3
b00000000000000000000000000000000 9
#369
01
#370
b00000000000000000001001011000000 +
b00000000000000000000000000001010 -
11
b100 3
b00000000000000000000001111101000 9
#371
01
#372
b00000000000000000000000000001001 -
11
b000 3
b00000000000000000000000000000000 9
#373
01
#374
b00000000000000000000000000001000 -
11
#375
01
#376
b00000000000000000000000000000111 -
b00000000000000000000000000000001 0
11
15
#377
01
#378
b00000000000000000000000000000110 -
b00000000000000000000000000000010 0
11
#379
01
#380
b00000000000000000000011001000000 ,
b00000000000000000000000000000101 -
b11111111111111111111111111111111 .
b00000000000000000000011001000000 /
b00000000000000000000000000000011 0
11
b111 8
#381
01
#382
b00000000000000000000110010000000 +
b00000000000000000000000000000000 ,
b00000000000000000000000000000100 -
b00000000000000000000000000000100 .
b00000000000000000000000000000000 /
b00000000000000000000000000000100 0
11
b000 8
#383
01
#384
b00000000000000000000000000000011 -
b00000000000000000000000000000101 0
11
#385
01
#386
b00000000000000000000000000000010 -
b00000000000000000000000000000110 0
11
#387
01
#388
b00000000000000000000000000000001 -
b00000000000000000000000000000111 0
11
#389
01
#390
b00000000000000000000000000000000 -
b00000000000000000000000000001000 0
11
#391
01
#392
b00000000000000000000011001000000 ,
b11111111111111111111111111111111 -
b11111111111111111111111111111111 .
b00000000000000000000011001000000 /
b00000000000000000000000000001001 0
11
b111 8
#393
01
#394
b00000000000000000000011001000000 +
b11111111111111111111111111111110 -
b00000000000000000000000000001010 0
11
b0111 6
#395
01
#396
b00000000000000000000000000000000 +
b00000000000000000000000000000000 ,
b11111111111111111111111111111101 -
b00000000000000000000000000000000 /
b00000000000000000000000000001011 0
11
b0000 6
b000 8
